swaywall/main.py
swaywall-0.3.0.dist-info/LICENSE
swaywall-0.3.0.dist-info/METADATA
swaywall-0.3.0.dist-info/WHEEL
swaywall-0.3.0.dist-info/entry_points.txt
swaywall-0.3.0.dist-info/RECORD
