Metadata-Version: 2.3
Name: swaywall
Version: 0.3.0
Summary: An intelligent wallpaper switcher for swaywm
License: GPL-3.0-only
Keywords: sway,swaywm,wayland,wallpaper,automation
Author: cycneuramus
Author-email: <56681631+cycneuramus@users.noreply.github.com>
Requires-Python: >=3.6
Classifier: License :: OSI Approved :: GNU General Public License v3 (GPLv3)
Classifier: Programming Language :: Python :: 3
Classifier: Programming Language :: Python :: 3.6
Classifier: Programming Language :: Python :: 3.7
Classifier: Programming Language :: Python :: 3.8
Classifier: Programming Language :: Python :: 3.9
Classifier: Programming Language :: Python :: 3.10
Classifier: Programming Language :: Python :: 3.11
Classifier: Programming Language :: Python :: 3.12
Classifier: Programming Language :: Python :: 3.13
Project-URL: Repository, https://github.com/cycneuramus/swaywall
